spotifyapi/Album.py
spotifyapi/Artist.py
spotifyapi/Exception.py
spotifyapi/Oauth.py
spotifyapi/Playlist.py
spotifyapi/Track.py
spotifyapi/User.py
spotifyapi/Util.py
spotifyapi/__init__.py
spotify_api.py-0.0.3.dist-info/LICENSE
spotify_api.py-0.0.3.dist-info/METADATA
spotify_api.py-0.0.3.dist-info/WHEEL
spotify_api.py-0.0.3.dist-info/top_level.txt
spotify_api.py-0.0.3.dist-info/RECORD
