Metadata-Version: 2.1
Name: spotify-api.py
Version: 0.0.3
Summary: A simple wrapper for spotify api written in python!
Home-page: https://github.com/spotify-api/spotify-api.py
License: MIT
Keywords: spotifyapi,spotify-api.py,spotify
Platform: UNKNOWN
Classifier: License :: OSI Approved :: MIT License
Classifier: Programming Language :: Python :: 3
Classifier: Programming Language :: Python :: 3.7
